streammachine_io_streammachine_schemas_demo_v1/__init__.py
streammachine_io_streammachine_schemas_demo_v1/schema.avsc
streammachine_io_streammachine_schemas_demo_v1/schema_classes.py
streammachine_io_streammachine_schemas_demo_v1/io/__init__.py
streammachine_io_streammachine_schemas_demo_v1/io/streammachine/__init__.py
streammachine_io_streammachine_schemas_demo_v1/io/streammachine/schemas/__init__.py
streammachine_io_streammachine_schemas_demo_v1/io/streammachine/schemas/demo/__init__.py
streammachine_io_streammachine_schemas_demo_v1/io/streammachine/schemas/demo/v1/__init__.py
streammachine_schemas_demo_avro-1.0.2.dist-info/METADATA
streammachine_schemas_demo_avro-1.0.2.dist-info/WHEEL
streammachine_schemas_demo_avro-1.0.2.dist-info/top_level.txt
streammachine_schemas_demo_avro-1.0.2.dist-info/RECORD
